{
    "date": "2008-02-07",
    "num_hubs": 150,
    "num_total_pkgs": 2604,
    "delivered": 996,
    "avg_pkg_per_trip": 3.373134328358209,
    "standard_deviation_pkg_per_trip": 3.1885327224688162,
    "max_packages_in_one_trip": 10,
    "trips_with_packages": 268,
    "success_rate_24h": 0.3817204301075269,
    "success_rate_eod": 0.37672811059907835,
    "success_num_24": 994,
    "success_num_eod": 981,
    "success_num_nodeadline": 996,
    "total_success_rate": 0.3824884792626728,
    "avg_delivery_time_hours": 5.124065953451026,
    "avg_delivery_time_hours_24h": 5.08568293461016,
    "avg_delivery_time_hours_EOD": 4.902789286515178
}