{
    "date": "2013-01-22",
    "num_hubs": 20,
    "num_total_pkgs": 32922,
    "delivered": 28244,
    "avg_pkg_per_trip": 5.211332070707071,
    "standard_deviation_pkg_per_trip": 3.684530056287863,
    "max_packages_in_one_trip": 10,
    "trips_with_packages": 6336,
    "success_rate_24h": 0.8579065670372396,
    "success_rate_eod": 0.8579065670372396,
    "success_num_24": 28244,
    "success_num_eod": 28244,
    "success_num_nodeadline": 28244,
    "total_success_rate": 0.8579065670372396,
    "avg_delivery_time_hours": 0.7331005856266032,
    "avg_delivery_time_hours_24h": 0.7331005856266032,
    "avg_delivery_time_hours_EOD": 0.7331005856266032
}