{
    "date": "2008-02-05",
    "num_hubs": 80,
    "num_total_pkgs": 3377,
    "delivered": 3325,
    "avg_pkg_per_trip": 2.5140811455847256,
    "standard_deviation_pkg_per_trip": 2.489628568419365,
    "max_packages_in_one_trip": 10,
    "trips_with_packages": 2095,
    "success_rate_24h": 0.9843055966834469,
    "success_rate_eod": 0.9786793011548712,
    "success_num_24": 3324,
    "success_num_eod": 3305,
    "success_num_nodeadline": 3325,
    "total_success_rate": 0.9846017175007403,
    "avg_delivery_time_hours": 4.316197743368421,
    "avg_delivery_time_hours_24h": 4.3075987057073135,
    "avg_delivery_time_hours_EOD": 4.237148607319213
}