{
    "date": "2013-01-22",
    "num_hubs": 15,
    "num_total_pkgs": 96057,
    "delivered": 88802,
    "avg_pkg_per_trip": 6.714134125636672,
    "standard_deviation_pkg_per_trip": 3.6645597306309194,
    "max_packages_in_one_trip": 10,
    "trips_with_packages": 18848,
    "success_rate_24h": 0.9244719281260085,
    "success_rate_eod": 0.9231185650186868,
    "success_num_24": 88802,
    "success_num_eod": 88672,
    "success_num_nodeadline": 88802,
    "total_success_rate": 0.9244719281260085,
    "avg_delivery_time_hours": 1.8596414769632692,
    "avg_delivery_time_hours_24h": 1.8596414769632692,
    "avg_delivery_time_hours_EOD": 1.8409082410521735
}