{
    "date": "2013-01-23",
    "num_hubs": 30,
    "num_total_pkgs": 37763,
    "delivered": 28337,
    "avg_pkg_per_trip": 4.363332476214965,
    "standard_deviation_pkg_per_trip": 3.4767201839695194,
    "max_packages_in_one_trip": 10,
    "trips_with_packages": 7778,
    "success_rate_24h": 0.7503905939676403,
    "success_rate_eod": 0.7503905939676403,
    "success_num_24": 28337,
    "success_num_eod": 28337,
    "success_num_nodeadline": 28337,
    "total_success_rate": 0.7503905939676403,
    "avg_delivery_time_hours": 0.7475160831026082,
    "avg_delivery_time_hours_24h": 0.7475160831026082,
    "avg_delivery_time_hours_EOD": 0.7475160831026082
}